demo/__init__.py
demo/conftest.py
demo/pytest.ini
demo/bin/__init__.py
demo/bin/webdrivers/__init__.py
demo/conf/__init__.py
demo/conf/debug.xml
demo/conf/demo.xml
demo/conf/global_conf.ini
demo/conf/testbed/__init__.py
demo/conf/testbed/testbed_demo.xml
demo/conf/testset/__init__.py
demo/conf/testset/testset_demo.xml
demo/features/__init__.py
demo/features/om/__init__.py
demo/features/om/login_page.py
demo/features/om/file_store/__init__.py
demo/features/om/object_store/__init__.py
demo/features/om/object_store/bucket_mgr/__init__.py
demo/features/om/object_store/bucket_mgr/bucket_list_page.py
demo/features/om/object_store/obj_mgr/__init__.py
demo/features/om/object_store/obj_mgr/upload.py
demo/features/toolkit/__init__.py
demo/features/toolkit/cli.py
demo/testcase/__init__.py
demo/testcase/om/__init__.py
demo/testcase/om/file_store/__init__.py
demo/testcase/om/file_store/file_directory/__init__.py
demo/testcase/om/file_store/file_directory/test_create_file_dir.py
demo/testcase/om/file_store/file_share/__init__.py
demo/testcase/om/file_store/file_share/test_create_file_share.py
demo/testcase/om/file_store/file_user/__init__.py
demo/testcase/om/file_store/file_user/test_create_file_user.py
demo/testcase/om/home_page/__init__.py
demo/testcase/om/home_page/test_home.py
demo/testcase/om/login/__init__.py
demo/testcase/om/login/test_login.py
demo/testcase/om/login/steps/__init__.py
demo/testcase/om/login/steps/api.py
demo/testcase/om/login/steps/ui.py
demo/testcase/om/object_store/__init__.py
demo/testcase/om/object_store/bucket/__init__.py
demo/testcase/om/object_store/bucket/test_bucket_create.py
demo/testcase/om/object_store/object/__init__.py
demo/testcase/om/object_store/object/test_object_upload.py
demo/testcase/performance/__init__.py
demo/testcase/performance/object_store/__init__.py
demo/testcase/protocol/__init__.py
demo/testcase/protocol/file_store/__init__.py
demo/testcase/protocol/file_store/cifs/__init__.py
flexrunner-1.0.9.dist-info/LICENSE
flexrunner-1.0.9.dist-info/METADATA
flexrunner-1.0.9.dist-info/WHEEL
flexrunner-1.0.9.dist-info/entry_points.txt
flexrunner-1.0.9.dist-info/top_level.txt
flexrunner-1.0.9.dist-info/RECORD
